Metadata-Version: 2.1
Name: vertx-eventbus-bridge-starter
Version: 1.0.3
Summary: Starter used to start an EventBus bridge for testing
Home-page: https://github.com/gaol/test-eventbus-bridge
Author: Lin Gao
Author-email: aoingl@gmail.com
License: Apache Software License 2.0
Platform: UNKNOWN
